{
    "Version": "1.2",
    "Data": {
        "Source": "e:\\epic\\projects\\frozen\\sdks\\ff_plugins_mobile\\plugins\\ff_pdfgen\\source\\ff_pdfgen\\thirdparty\\pdfgen\\pdfgen.c",
        "ProvidedModule": "",
        "Includes": [
            "c:\\program files (x86)\\windows kits\\10\\include\\10.0.22000.0\\shared\\basetsd.h",
            "c:\\program files (x86)\\windows kits\\10\\include\\10.0.22000.0\\ucrt\\ctype.h",
            "c:\\program files (x86)\\windows kits\\10\\include\\10.0.22000.0\\ucrt\\corecrt.h",
            "c:\\program files\\microsoft visual studio\\2022\\enterprise\\vc\\tools\\msvc\\14.34.31933\\include\\vcruntime.h",
            "c:\\program files\\microsoft visual studio\\2022\\enterprise\\vc\\tools\\msvc\\14.34.31933\\include\\sal.h",
            "c:\\program files\\microsoft visual studio\\2022\\enterprise\\vc\\tools\\msvc\\14.34.31933\\include\\concurrencysal.h",
            "c:\\program files\\microsoft visual studio\\2022\\enterprise\\vc\\tools\\msvc\\14.34.31933\\include\\vadefs.h",
            "c:\\program files (x86)\\windows kits\\10\\include\\10.0.22000.0\\ucrt\\corecrt_wctype.h",
            "c:\\program files (x86)\\windows kits\\10\\include\\10.0.22000.0\\ucrt\\errno.h",
            "c:\\program files (x86)\\windows kits\\10\\include\\10.0.22000.0\\ucrt\\inttypes.h",
            "c:\\program files\\microsoft visual studio\\2022\\enterprise\\vc\\tools\\msvc\\14.34.31933\\include\\stdint.h",
            "c:\\program files (x86)\\windows kits\\10\\include\\10.0.22000.0\\ucrt\\locale.h",
            "c:\\program files (x86)\\windows kits\\10\\include\\10.0.22000.0\\ucrt\\math.h",
            "c:\\program files (x86)\\windows kits\\10\\include\\10.0.22000.0\\ucrt\\corecrt_math.h",
            "c:\\program files (x86)\\windows kits\\10\\include\\10.0.22000.0\\ucrt\\corecrt_math_defines.h",
            "c:\\program files\\microsoft visual studio\\2022\\enterprise\\vc\\tools\\msvc\\14.34.31933\\include\\stdarg.h",
            "c:\\program files\\microsoft visual studio\\2022\\enterprise\\vc\\tools\\msvc\\14.34.31933\\include\\stdbool.h",
            "c:\\program files (x86)\\windows kits\\10\\include\\10.0.22000.0\\ucrt\\stddef.h",
            "c:\\program files (x86)\\windows kits\\10\\include\\10.0.22000.0\\ucrt\\stdio.h",
            "c:\\program files (x86)\\windows kits\\10\\include\\10.0.22000.0\\ucrt\\corecrt_wstdio.h",
            "c:\\program files (x86)\\windows kits\\10\\include\\10.0.22000.0\\ucrt\\corecrt_stdio_config.h",
            "c:\\program files (x86)\\windows kits\\10\\include\\10.0.22000.0\\ucrt\\stdlib.h",
            "c:\\program files (x86)\\windows kits\\10\\include\\10.0.22000.0\\ucrt\\corecrt_malloc.h",
            "c:\\program files (x86)\\windows kits\\10\\include\\10.0.22000.0\\ucrt\\corecrt_search.h",
            "c:\\program files (x86)\\windows kits\\10\\include\\10.0.22000.0\\ucrt\\corecrt_wstdlib.h",
            "c:\\program files\\microsoft visual studio\\2022\\enterprise\\vc\\tools\\msvc\\14.34.31933\\include\\limits.h",
            "c:\\program files (x86)\\windows kits\\10\\include\\10.0.22000.0\\ucrt\\string.h",
            "c:\\program files (x86)\\windows kits\\10\\include\\10.0.22000.0\\ucrt\\corecrt_memory.h",
            "c:\\program files (x86)\\windows kits\\10\\include\\10.0.22000.0\\ucrt\\corecrt_memcpy_s.h",
            "c:\\program files\\microsoft visual studio\\2022\\enterprise\\vc\\tools\\msvc\\14.34.31933\\include\\vcruntime_string.h",
            "c:\\program files (x86)\\windows kits\\10\\include\\10.0.22000.0\\ucrt\\corecrt_wstring.h",
            "c:\\program files (x86)\\windows kits\\10\\include\\10.0.22000.0\\ucrt\\sys\\stat.h",
            "c:\\program files (x86)\\windows kits\\10\\include\\10.0.22000.0\\ucrt\\sys\\types.h",
            "c:\\program files (x86)\\windows kits\\10\\include\\10.0.22000.0\\ucrt\\time.h",
            "c:\\program files (x86)\\windows kits\\10\\include\\10.0.22000.0\\ucrt\\corecrt_wtime.h",
            "e:\\epic\\projects\\frozen\\sdks\\ff_plugins_mobile\\plugins\\ff_pdfgen\\source\\ff_pdfgen\\thirdparty\\pdfgen\\pdfgen.h"
        ]
    }
}